graphs_Sergio_343/__init__.py
graphs_Sergio_343/heapq.py
graphs_Sergio_343/sp.py
graphs_sergio_343-0.0.1.dist-info/METADATA
graphs_sergio_343-0.0.1.dist-info/WHEEL
graphs_sergio_343-0.0.1.dist-info/RECORD
