Metadata-Version: 2.4
Name: graphs_Sergio_343
Version: 0.0.1
Summary: Graph alogrithms package Dijkstra
Project-URL: Homepage, https://github.com/pypa/sampleproject
Project-URL: Bug Tracker, https://github.com/pypa/sampleproject/issues
Author-email: Sergio R Ramirez-Beltran <sergiorrbeltran@gmail.com>
Classifier: License :: OSI Approved :: MIT License
Classifier: Operating System :: OS Independent
Classifier: Programming Language :: Python :: 3
Requires-Python: >=3.7
